odoo/addons/stock_available_unreserved/README.rst
odoo/addons/stock_available_unreserved/__init__.py
odoo/addons/stock_available_unreserved/__manifest__.py
odoo/addons/stock_available_unreserved/i18n/ca.po
odoo/addons/stock_available_unreserved/i18n/de.po
odoo/addons/stock_available_unreserved/i18n/el_GR.po
odoo/addons/stock_available_unreserved/i18n/es.po
odoo/addons/stock_available_unreserved/i18n/es_ES.po
odoo/addons/stock_available_unreserved/i18n/es_MX.po
odoo/addons/stock_available_unreserved/i18n/eu.po
odoo/addons/stock_available_unreserved/i18n/fi.po
odoo/addons/stock_available_unreserved/i18n/fr.po
odoo/addons/stock_available_unreserved/i18n/fr_CH.po
odoo/addons/stock_available_unreserved/i18n/fr_FR.po
odoo/addons/stock_available_unreserved/i18n/gl.po
odoo/addons/stock_available_unreserved/i18n/hr.po
odoo/addons/stock_available_unreserved/i18n/hr_HR.po
odoo/addons/stock_available_unreserved/i18n/it.po
odoo/addons/stock_available_unreserved/i18n/nl.po
odoo/addons/stock_available_unreserved/i18n/nl_NL.po
odoo/addons/stock_available_unreserved/i18n/pt.po
odoo/addons/stock_available_unreserved/i18n/pt_BR.po
odoo/addons/stock_available_unreserved/i18n/ro.po
odoo/addons/stock_available_unreserved/i18n/ru.po
odoo/addons/stock_available_unreserved/i18n/sl.po
odoo/addons/stock_available_unreserved/i18n/tr.po
odoo/addons/stock_available_unreserved/i18n/tr_TR.po
odoo/addons/stock_available_unreserved/i18n/vi_VN.po
odoo/addons/stock_available_unreserved/i18n/zh_CN.po
odoo/addons/stock_available_unreserved/models/__init__.py
odoo/addons/stock_available_unreserved/models/product.py
odoo/addons/stock_available_unreserved/models/quant.py
odoo/addons/stock_available_unreserved/static/description/icon.png
odoo/addons/stock_available_unreserved/tests/__init__.py
odoo/addons/stock_available_unreserved/tests/test_stock_available_unreserved.py
odoo/addons/stock_available_unreserved/views/product_view.xml
odoo11_addon_stock_available_unreserved-11.0.1.0.0.dist-info/DESCRIPTION.rst
odoo11_addon_stock_available_unreserved-11.0.1.0.0.dist-info/METADATA
odoo11_addon_stock_available_unreserved-11.0.1.0.0.dist-info/RECORD
odoo11_addon_stock_available_unreserved-11.0.1.0.0.dist-info/WHEEL
odoo11_addon_stock_available_unreserved-11.0.1.0.0.dist-info/metadata.json
odoo11_addon_stock_available_unreserved-11.0.1.0.0.dist-info/top_level.txt
